ModuleManager/ModuleManager.py
ModuleManager/__init__.py
ModuleManager-0.0.1.dist-info/LICENSE
ModuleManager-0.0.1.dist-info/METADATA
ModuleManager-0.0.1.dist-info/WHEEL
ModuleManager-0.0.1.dist-info/top_level.txt
ModuleManager-0.0.1.dist-info/RECORD
